{"name":"Littlebox","tagline":"Android app for simple seamless sharing of your files within Intranet/LAN","body":"Littlebox aims to provide simple seamless sharing of your files within Intranet/LAN.\r\n\r\n> **This application is in alpha stage. If you come across any bug, please do report them at [littlebox/issues](https://github.com/harshjv/littlebox/issues)**\r\n\r\n\r\n# Screenshots\r\n\r\n![Littlebox Android App Screenshot](http://i.imgur.com/XDY8TiW.png \"Littlebox Android App Screenshot\")\r\n\r\n![Littlebox Screenshot](http://i.imgur.com/ExQPBVs.png \"Littlebox Screenshot\")\r\n\r\n![Littlebox File Uploads Screenshot](http://i.imgur.com/JhwUXsq.png \"Littlebox File Uploads Screenshot\")\r\n\r\n\r\n# Try it!\r\n\r\n[Download Littlebox](http://bit.ly/littlebox-alpha)\r\n\r\n\r\n# Source\r\n\r\nCurrently, the source is not made publicly available (closed source). In near future, source may be available publicly (open source). Main objective of this repository, for now, is to provide [issue tracker](https://github.com/harshjv/littlebox/issues).\r\n\r\n\r\n# Author\r\n\r\n[Harsh Vakharia](https://twitter.com/harshjv)\r\n","google":"","note":"Don't delete this file! It's used internally to help with page regeneration."}